yoctoEC2/__init__.py
yoctoEC2/core.py
yoctoEC2-0.2.1.dist-info/LICENSE.txt
yoctoEC2-0.2.1.dist-info/METADATA
yoctoEC2-0.2.1.dist-info/WHEEL
yoctoEC2-0.2.1.dist-info/entry_points.txt
yoctoEC2-0.2.1.dist-info/top_level.txt
yoctoEC2-0.2.1.dist-info/RECORD
