Metadata-Version: 2.1
Name: yoctoEC2
Version: 0.2.1
Summary: A yocto EC2 Python project
Home-page: https://github.com/ttruongatl/yocto-ec2-utils
Author: Thanh Truong
Author-email: thanh.truong@smisy.io
License: UNKNOWN
Project-URL: Bug Reports, https://github.com/ttruongatl/yocto-ec2-utils/issues
Project-URL: Source, https://github.com/ttruongatl/yocto-ec2-utils/
Keywords: yoctoEC2 build tools development
Platform: UNKNOWN
Requires-Dist: Click (~=7.0)
Requires-Dist: fabric (~=2.4.0)
Requires-Dist: boto3 (~=1.9.188)
